{
  "_fv": 57,
  "_type": "biome",
  "definition": {
    "name": "Forest Build Plate",
    "groundBlock": {
      "value": "Blocks.GRASS"
    },
    "undergroundBlock": {
      "value": "Blocks.DIRT#0"
    },
    "underwaterBlock": {
      "value": ""
    },
    "grassColor": {
      "value": -8857051,
      "falpha": 0.0
    },
    "foliageColor": {
      "value": -8857051,
      "falpha": 0.0
    },
    "ambientSound": {
      "value": ""
    },
    "additionsSound": {
      "value": ""
    },
    "music": {
      "value": ""
    },
    "moodSound": {
      "value": ""
    },
    "moodSoundDelay": 0,
    "spawnParticles": false,
    "particleToSpawn": {
      "value": "EXPLOSION_NORMAL"
    },
    "particlesProbability": 0.0,
    "rainingPossibility": 0.0,
    "temperature": 0.5,
    "spawnBiome": false,
    "spawnInCaves": false,
    "spawnBiomeNether": false,
    "genTemperature": {
      "min": -0.2,
      "max": 0.2
    },
    "genHumidity": {
      "min": -1.2,
      "max": -0.8
    },
    "genContinentalness": {
      "min": 0.31,
      "max": 0.71
    },
    "genErosion": {
      "min": 0.7,
      "max": 1.0999999999999999
    },
    "genWeirdness": {
      "min": -1.1705115363306802,
      "max": -0.7705115363306803
    },
    "treesPerChunk": 5,
    "vanillaTreeType": "Default",
    "treeType": 0,
    "minHeight": 7,
    "treeStem": {
      "value": ""
    },
    "treeBranch": {
      "value": ""
    },
    "treeVines": {
      "value": ""
    },
    "treeFruits": {
      "value": ""
    },
    "defaultFeatures": [
      "Caves",
      "MonsterRooms",
      "Structures",
      "Ores",
      "Lakes",
      "DefaultFlowers",
      "DoubleFlowers",
      "ExtraDefaultFlowers",
      "OakTreesFlowersGrass",
      "Ores",
      "FrozenTopLayer",
      "ForestGrass"
    ],
    "spawnStronghold": false,
    "spawnMineshaft": false,
    "spawnMineshaftMesa": false,
    "spawnPillagerOutpost": false,
    "villageType": "plains",
    "spawnWoodlandMansion": false,
    "spawnJungleTemple": false,
    "spawnDesertPyramid": false,
    "spawnSwampHut": false,
    "spawnIgloo": false,
    "spawnOceanMonument": false,
    "spawnShipwreck": false,
    "spawnShipwreckBeached": false,
    "spawnBuriedTreasure": false,
    "oceanRuinType": "NONE",
    "spawnNetherBridge": false,
    "spawnNetherFossil": false,
    "spawnBastionRemnant": false,
    "spawnEndCity": false,
    "spawnRuinedPortal": "NONE",
    "spawnEntries": [
      {
        "entity": {
          "value": "CUSTOM:MuddyPig"
        },
        "minGroup": 2,
        "maxGroup": 4,
        "weight": 3,
        "spawnType": "creature"
      },
      {
        "entity": {
          "value": "CUSTOM:Cluckshroom"
        },
        "minGroup": 2,
        "maxGroup": 4,
        "weight": 10,
        "spawnType": "creature"
      },
      {
        "entity": {
          "value": "CUSTOM:FurnaceGolem"
        },
        "minGroup": 1,
        "maxGroup": 1,
        "weight": 3,
        "spawnType": "creature"
      },
      {
        "entity": {
          "value": "CUSTOM:MelonGolem"
        },
        "minGroup": 1,
        "maxGroup": 2,
        "weight": 10,
        "spawnType": "creature"
      },
      {
        "entity": {
          "value": "CUSTOM:Moobloom"
        },
        "minGroup": 2,
        "maxGroup": 3,
        "weight": 10,
        "spawnType": "creature"
      },
      {
        "entity": {
          "value": "CUSTOM:AlbinoCow"
        },
        "minGroup": 2,
        "maxGroup": 3,
        "weight": 15,
        "spawnType": "creature"
      },
      {
        "entity": {
          "value": "CUSTOM:AmberChicken"
        },
        "minGroup": 2,
        "maxGroup": 3,
        "weight": 15,
        "spawnType": "creature"
      },
      {
        "entity": {
          "value": "CUSTOM:MidnightChicken"
        },
        "minGroup": 2,
        "maxGroup": 3,
        "weight": 15,
        "spawnType": "creature"
      },
      {
        "entity": {
          "value": "CUSTOM:StormyChicken"
        },
        "minGroup": 2,
        "maxGroup": 3,
        "weight": 15,
        "spawnType": "creature"
      },
      {
        "entity": {
          "value": "CUSTOM:SpottedPig"
        },
        "minGroup": 2,
        "maxGroup": 3,
        "weight": 15,
        "spawnType": "creature"
      },
      {
        "entity": {
          "value": "CUSTOM:PieBaldPig"
        },
        "minGroup": 2,
        "maxGroup": 3,
        "weight": 15,
        "spawnType": "creature"
      },
      {
        "entity": {
          "value": "CUSTOM:PalePig"
        },
        "minGroup": 2,
        "maxGroup": 3,
        "weight": 15,
        "spawnType": "creature"
      },
      {
        "entity": {
          "value": "CUSTOM:AshenCow"
        },
        "minGroup": 2,
        "maxGroup": 3,
        "weight": 15,
        "spawnType": "creature"
      },
      {
        "entity": {
          "value": "CUSTOM:SunsetCow"
        },
        "minGroup": 2,
        "maxGroup": 3,
        "weight": 15,
        "spawnType": "creature"
      },
      {
        "entity": {
          "value": "CUSTOM:PinkFootedPig"
        },
        "minGroup": 2,
        "maxGroup": 3,
        "weight": 15,
        "spawnType": "creature"
      }
    ]
  }
}